README.md
setup.py
pvlv_img_builder/__init__.py
pvlv_img_builder/draw_support.py
pvlv_img_builder/graph.py
pvlv_img_builder/level_card.py
pvlv_img_builder/level_up_card.py
pvlv_img_builder/ranking_card.py
pvlv_img_builder.egg-info/PKG-INFO
pvlv_img_builder.egg-info/SOURCES.txt
pvlv_img_builder.egg-info/dependency_links.txt
pvlv_img_builder.egg-info/requires.txt
pvlv_img_builder.egg-info/top_level.txt
pvlv_img_builder/configurations/__init__.py
pvlv_img_builder/configurations/configuration.py
pvlv_img_builder/fonts/__init__.py
pvlv_img_builder/modules/__init__.py
pvlv_img_builder/modules/level_utils.py
pvlv_img_builder/utils/__init__.py
pvlv_img_builder/utils/formatting.py
pvlv_img_builder/utils/positions.py
test/test.py